solan/__init__.py
solan/core.py
solan-0.1.1.dist-info/DESCRIPTION.rst
solan-0.1.1.dist-info/METADATA
solan-0.1.1.dist-info/RECORD
solan-0.1.1.dist-info/WHEEL
solan-0.1.1.dist-info/entry_points.txt
solan-0.1.1.dist-info/metadata.json
solan-0.1.1.dist-info/top_level.txt
