Metadata-Version: 2.0
Name: solan
Version: 0.1.1
Summary: Solan
Home-page: https://github.com/OpenCode/solan
Author: Francesco Apruzzese
Author-email: cescoap@gmail.com
License: AGPL
Keywords: solan share sharing lan
Platform: UNKNOWN
Classifier: Development Status :: 2 - Pre-Alpha
Classifier: Intended Audience :: Developers
Classifier: License :: OSI Approved :: GNU Affero General Public License v3 or later (AGPLv3+)
Classifier: Topic :: Communications :: File Sharing
Classifier: Programming Language :: Python :: 3.6
Classifier: Programming Language :: Python :: 3.7
Requires-Dist: click
Requires-Dist: pyngrok
